{
  "index": 1351,
  "dataframe_iter_index": 1351,
  "image_path": "./datasets/sAFRICANWILDLIFE_FLUXFP8/images/1351.jpg",
  "image_width": 640,
  "image_height": 640,
  "ground_truth_class": "rhino",
  "grounding_prompt": "rhino",
  "timestamp": "2026-05-04T20:17:15.597750",
  "num_detections": 4,
  "detections": [
    {
      "detection_id": 0,
      "class_name": "rhino",
      "yolo_class_id": 2,
      "confidence": 0.8284711241722107,
      "bbox_xyxy": [
        347.3480224609375,
        396.2926330566406,
        491.7254638671875,
        476.2265930175781
      ],
      "bbox_yolo": [
        0.6555261611938477,
        0.6816556453704834,
        0.22558975219726562,
        0.1248968094587326
      ],
      "bbox_width_px": 144.37744140625,
      "bbox_height_px": 79.9339599609375
    },
    {
      "detection_id": 1,
      "class_name": "rhino",
      "yolo_class_id": 2,
      "confidence": 0.8067894577980042,
      "bbox_xyxy": [
        479.5650634765625,
        398.8407287597656,
        608.473388671875,
        462.4407653808594
      ],
      "bbox_yolo": [
        0.8500300645828247,
        0.6728761792182922,
        0.20141926407814026,
        0.09937505424022675
      ],
      "bbox_width_px": 128.9083251953125,
      "bbox_height_px": 63.60003662109375
    },
    {
      "detection_id": 2,
      "class_name": "rhino",
      "yolo_class_id": 2,
      "confidence": 0.8073137402534485,
      "bbox_xyxy": [
        186.2076416015625,
        396.49908447265625,
        330.01123046875,
        464.03802490234375
      ],
      "bbox_yolo": [
        0.40329599380493164,
        0.6722946166992188,
        0.22469310462474823,
        0.10552959144115448
      ],
      "bbox_width_px": 143.8035888671875,
      "bbox_height_px": 67.5389404296875
    },
    {
      "detection_id": 3,
      "class_name": "rhino",
      "yolo_class_id": 2,
      "confidence": 0.8219342827796936,
      "bbox_xyxy": [
        53.53282928466797,
        394.4415283203125,
        189.79083251953125,
        464.977294921875
      ],
      "bbox_yolo": [
        0.19009661674499512,
        0.6714209318161011,
        0.21290311217308044,
        0.11021213233470917
      ],
      "bbox_width_px": 136.25799560546875,
      "bbox_height_px": 70.5357666015625
    }
  ]
}