{
  "index": 68,
  "dataframe_iter_index": 68,
  "image_path": "./datasets/sAFRICANWILDLIFE_FLUXFP8/images/68.jpg",
  "image_width": 640,
  "image_height": 640,
  "ground_truth_class": "buffalo",
  "grounding_prompt": "buffalo",
  "timestamp": "2026-05-04T20:02:02.744773",
  "num_detections": 1,
  "detections": [
    {
      "detection_id": 0,
      "class_name": "buffalo",
      "yolo_class_id": 0,
      "confidence": 0.9498341083526611,
      "bbox_xyxy": [
        128.1524658203125,
        166.36468505859375,
        568.2745361328125,
        541.4221801757812
      ],
      "bbox_yolo": [
        0.5440835952758789,
        0.5529584884643555,
        0.6876907348632812,
        0.5860273241996765
      ],
      "bbox_width_px": 440.1220703125,
      "bbox_height_px": 375.0574951171875
    }
  ]
}