{
  "index": 4291,
  "dataframe_iter_index": 4291,
  "image_path": "./datasets/sFERNANDO_FLUX29B/images/4291.png",
  "image_width": 640,
  "image_height": 640,
  "ground_truth_class": "speed_boat",
  "grounding_prompt": "boat",
  "timestamp": "2026-05-04T20:46:51.548984",
  "num_detections": 1,
  "detections": [
    {
      "detection_id": 0,
      "class_name": "speed_boat",
      "yolo_class_id": 10,
      "confidence": 0.9483720660209656,
      "bbox_xyxy": [
        202.04949951171875,
        297.83758544921875,
        398.39251708984375,
        425.25250244140625
      ],
      "bbox_yolo": [
        0.4690953195095062,
        0.5649141073226929,
        0.3067859709262848,
        0.1990858018398285
      ],
      "bbox_width_px": 196.343017578125,
      "bbox_height_px": 127.4149169921875
    }
  ]
}