{
  "index": 5012,
  "dataframe_iter_index": 5012,
  "image_path": "./datasets/sFERNANDO_FLUX29B/images/5012.png",
  "image_width": 640,
  "image_height": 640,
  "ground_truth_class": "sailboat",
  "grounding_prompt": "boat",
  "timestamp": "2026-05-04T21:00:34.535031",
  "num_detections": 1,
  "detections": [
    {
      "detection_id": 0,
      "class_name": "sailboat",
      "yolo_class_id": 8,
      "confidence": 0.8198688626289368,
      "bbox_xyxy": [
        259.10150146484375,
        189.29344177246094,
        370.29083251953125,
        392.10491943359375
      ],
      "bbox_yolo": [
        0.491712749004364,
        0.45421749353408813,
        0.17373332381248474,
        0.31689292192459106
      ],
      "bbox_width_px": 111.1893310546875,
      "bbox_height_px": 202.8114776611328
    }
  ]
}