{
  "index": 5048,
  "dataframe_iter_index": 5048,
  "image_path": "./datasets/sFERNANDO_FLUX29B/images/5048.png",
  "image_width": 640,
  "image_height": 640,
  "ground_truth_class": "sailboat",
  "grounding_prompt": "boat",
  "timestamp": "2026-05-04T21:01:14.943031",
  "num_detections": 1,
  "detections": [
    {
      "detection_id": 0,
      "class_name": "sailboat",
      "yolo_class_id": 8,
      "confidence": 0.70949387550354,
      "bbox_xyxy": [
        233.33836364746094,
        47.39814758300781,
        392.71832275390625,
        404.30584716796875
      ],
      "bbox_yolo": [
        0.48910680413246155,
        0.35289373993873596,
        0.2490311861038208,
        0.5576683282852173
      ],
      "bbox_width_px": 159.3799591064453,
      "bbox_height_px": 356.90771484375
    }
  ]
}