{
  "index": 5096,
  "dataframe_iter_index": 5096,
  "image_path": "./datasets/sFERNANDO_FLUX29B/images/5096.png",
  "image_width": 640,
  "image_height": 640,
  "ground_truth_class": "sailboat",
  "grounding_prompt": "boat",
  "timestamp": "2026-05-04T21:02:09.409856",
  "num_detections": 1,
  "detections": [
    {
      "detection_id": 0,
      "class_name": "sailboat",
      "yolo_class_id": 8,
      "confidence": 0.574820339679718,
      "bbox_xyxy": [
        242.6023406982422,
        0.1899566650390625,
        386.77642822265625,
        423.5496826171875
      ],
      "bbox_yolo": [
        0.4917021691799164,
        0.33104658126831055,
        0.2252720147371292,
        0.6614996194839478
      ],
      "bbox_width_px": 144.17408752441406,
      "bbox_height_px": 423.3597412109375
    }
  ]
}