{
  "index": 6454,
  "dataframe_iter_index": 6454,
  "image_path": "./datasets/sFERNANDO_FLUX29B/images/6454.png",
  "image_width": 640,
  "image_height": 640,
  "ground_truth_class": "industrial ship",
  "grounding_prompt": "boat",
  "timestamp": "2026-05-04T21:27:35.728388",
  "num_detections": 3,
  "detections": [
    {
      "detection_id": 0,
      "class_name": "industrial ship",
      "yolo_class_id": 3,
      "confidence": 0.6804766654968262,
      "bbox_xyxy": [
        93.13451385498047,
        273.2123107910156,
        201.254638671875,
        336.5323181152344
      ],
      "bbox_yolo": [
        0.22999152541160583,
        0.47636300325393677,
        0.16893769800662994,
        0.0989375114440918
      ],
      "bbox_width_px": 108.12012481689453,
      "bbox_height_px": 63.32000732421875
    },
    {
      "detection_id": 1,
      "class_name": "industrial ship",
      "yolo_class_id": 3,
      "confidence": 0.6042581796646118,
      "bbox_xyxy": [
        250.21044921875,
        280.2843322753906,
        387.82672119140625,
        372.9813537597656
      ],
      "bbox_yolo": [
        0.4984665513038635,
        0.5103638172149658,
        0.2150254249572754,
        0.1448390930891037
      ],
      "bbox_width_px": 137.61627197265625,
      "bbox_height_px": 92.697021484375
    },
    {
      "detection_id": 2,
      "class_name": "industrial ship",
      "yolo_class_id": 3,
      "confidence": 0.5235975980758667,
      "bbox_xyxy": [
        437.4950866699219,
        281.2712707519531,
        559.7012939453125,
        346.4921569824219
      ],
      "bbox_yolo": [
        0.7790597081184387,
        0.4904401898384094,
        0.19094720482826233,
        0.1019076332449913
      ],
      "bbox_width_px": 122.20620727539062,
      "bbox_height_px": 65.22088623046875
    }
  ]
}