{
  "index": 6538,
  "dataframe_iter_index": 6538,
  "image_path": "./datasets/sFERNANDO_FLUX29B/images/6538.png",
  "image_width": 640,
  "image_height": 640,
  "ground_truth_class": "industrial ship",
  "grounding_prompt": "boat",
  "timestamp": "2026-05-04T21:29:09.667156",
  "num_detections": 3,
  "detections": [
    {
      "detection_id": 0,
      "class_name": "industrial ship",
      "yolo_class_id": 3,
      "confidence": 0.5827170610427856,
      "bbox_xyxy": [
        432.4850158691406,
        279.16259765625,
        566.1722412109375,
        362.23291015625
      ],
      "bbox_yolo": [
        0.7802009582519531,
        0.5010902285575867,
        0.2088862955570221,
        0.12979736924171448
      ],
      "bbox_width_px": 133.68722534179688,
      "bbox_height_px": 83.0703125
    },
    {
      "detection_id": 1,
      "class_name": "industrial ship",
      "yolo_class_id": 3,
      "confidence": 0.589153528213501,
      "bbox_xyxy": [
        250.03627014160156,
        260.8582763671875,
        385.73150634765625,
        374.0927734375
      ],
      "bbox_yolo": [
        0.49669355154037476,
        0.4960555136203766,
        0.2120238095521927,
        0.17692890763282776
      ],
      "bbox_width_px": 135.6952362060547,
      "bbox_height_px": 113.2344970703125
    },
    {
      "detection_id": 2,
      "class_name": "industrial ship",
      "yolo_class_id": 3,
      "confidence": 0.7852485775947571,
      "bbox_xyxy": [
        75.91045379638672,
        254.54136657714844,
        199.14208984375,
        371.72027587890625
      ],
      "bbox_yolo": [
        0.21488480269908905,
        0.48926693201065063,
        0.1925494372844696,
        0.18309204280376434
      ],
      "bbox_width_px": 123.23163604736328,
      "bbox_height_px": 117.17890930175781
    }
  ]
}