{
  "index": 6706,
  "dataframe_iter_index": 6706,
  "image_path": "./datasets/sFERNANDO_FLUX29B/images/6706.png",
  "image_width": 640,
  "image_height": 640,
  "ground_truth_class": "industrial ship",
  "grounding_prompt": "boat",
  "timestamp": "2026-05-04T21:32:17.339015",
  "num_detections": 3,
  "detections": [
    {
      "detection_id": 0,
      "class_name": "industrial ship",
      "yolo_class_id": 3,
      "confidence": 0.8028989434242249,
      "bbox_xyxy": [
        83.2314453125,
        255.94679260253906,
        203.86935424804688,
        370.34332275390625
      ],
      "bbox_yolo": [
        0.22429749369621277,
        0.48928913474082947,
        0.18849673867225647,
        0.1787445843219757
      ],
      "bbox_width_px": 120.63790893554688,
      "bbox_height_px": 114.39653015136719
    },
    {
      "detection_id": 1,
      "class_name": "industrial ship",
      "yolo_class_id": 3,
      "confidence": 0.7946221232414246,
      "bbox_xyxy": [
        255.06692504882812,
        258.4983215332031,
        386.0943298339844,
        377.8955993652344
      ],
      "bbox_yolo": [
        0.5009072422981262,
        0.4971827566623688,
        0.2047303169965744,
        0.18655824661254883
      ],
      "bbox_width_px": 131.02740478515625,
      "bbox_height_px": 119.39727783203125
    },
    {
      "detection_id": 2,
      "class_name": "industrial ship",
      "yolo_class_id": 3,
      "confidence": 0.5657318234443665,
      "bbox_xyxy": [
        431.5719909667969,
        281.3988952636719,
        553.9806518554688,
        363.2414855957031
      ],
      "bbox_yolo": [
        0.7699629664421082,
        0.5036252737045288,
        0.19126352667808533,
        0.1278790533542633
      ],
      "bbox_width_px": 122.40866088867188,
      "bbox_height_px": 81.84259033203125
    }
  ]
}