{
  "index": 8668,
  "dataframe_iter_index": 8668,
  "image_path": "./datasets/sFERNANDO_FLUX29B/images/8668.png",
  "image_width": 640,
  "image_height": 640,
  "ground_truth_class": "human powered boat",
  "grounding_prompt": "boat",
  "timestamp": "2026-05-04T22:09:17.244933",
  "num_detections": 1,
  "detections": [
    {
      "detection_id": 0,
      "class_name": "human powered boat",
      "yolo_class_id": 2,
      "confidence": 0.9513533711433411,
      "bbox_xyxy": [
        221.73239135742188,
        306.1756591796875,
        405.4891052246094,
        409.01690673828125
      ],
      "bbox_yolo": [
        0.49001678824424744,
        0.5587441921234131,
        0.28711986541748047,
        0.16068944334983826
      ],
      "bbox_width_px": 183.7567138671875,
      "bbox_height_px": 102.84124755859375
    }
  ]
}