{
  "index": 11416,
  "dataframe_iter_index": 11416,
  "image_path": "./datasets/sVOC_FLUXFP8/images/11416.png",
  "image_width": 640,
  "image_height": 640,
  "ground_truth_class": "person",
  "grounding_prompt": "person",
  "timestamp": "2026-05-22T14:13:29.655698",
  "num_detections": 1,
  "detections": [
    {
      "detection_id": 0,
      "class_name": "person",
      "yolo_class_id": 14,
      "confidence": 0.9143853783607483,
      "bbox_xyxy": [
        226.30267333984375,
        260.22320556640625,
        428.2969970703125,
        447.76824951171875
      ],
      "bbox_yolo": [
        0.5114060044288635,
        0.5531183481216431,
        0.3156161308288574,
        0.29303914308547974
      ],
      "bbox_width_px": 201.99432373046875,
      "bbox_height_px": 187.5450439453125
    }
  ]
}