{
  "index": 11454,
  "dataframe_iter_index": 11454,
  "image_path": "./datasets/sVOC_FLUXFP8/images/11454.png",
  "image_width": 640,
  "image_height": 640,
  "ground_truth_class": "person",
  "grounding_prompt": "person",
  "timestamp": "2026-05-22T14:14:23.603317",
  "num_detections": 4,
  "detections": [
    {
      "detection_id": 0,
      "class_name": "person",
      "yolo_class_id": 14,
      "confidence": 0.8572558760643005,
      "bbox_xyxy": [
        296.63323974609375,
        264.73260498046875,
        383.03326416015625,
        519.2408447265625
      ],
      "bbox_yolo": [
        0.5309894680976868,
        0.6124792695045471,
        0.13500003516674042,
        0.39766913652420044
      ],
      "bbox_width_px": 86.4000244140625,
      "bbox_height_px": 254.50823974609375
    },
    {
      "detection_id": 1,
      "class_name": "person",
      "yolo_class_id": 14,
      "confidence": 0.8511021137237549,
      "bbox_xyxy": [
        116.1100082397461,
        204.84571838378906,
        241.5738525390625,
        559.5023803710938
      ],
      "bbox_yolo": [
        0.2794405221939087,
        0.5971469283103943,
        0.19603726267814636,
        0.5541510581970215
      ],
      "bbox_width_px": 125.4638442993164,
      "bbox_height_px": 354.65667724609375
    },
    {
      "detection_id": 2,
      "class_name": "person",
      "yolo_class_id": 14,
      "confidence": 0.8546866774559021,
      "bbox_xyxy": [
        434.69927978515625,
        251.64022827148438,
        518.8744506835938,
        497.3300476074219
      ],
      "bbox_yolo": [
        0.7449795007705688,
        0.5851330161094666,
        0.13152369856834412,
        0.3838903307914734
      ],
      "bbox_width_px": 84.1751708984375,
      "bbox_height_px": 245.6898193359375
    },
    {
      "detection_id": 3,
      "class_name": "person",
      "yolo_class_id": 14,
      "confidence": 0.4313228726387024,
      "bbox_xyxy": [
        2.46268892288208,
        329.3133239746094,
        17.483154296875,
        369.3078918457031
      ],
      "bbox_yolo": [
        0.015582690015435219,
        0.5457978248596191,
        0.023469477891921997,
        0.062491513788700104
      ],
      "bbox_width_px": 15.020465850830078,
      "bbox_height_px": 39.99456787109375
    }
  ]
}