{
  "index": 13074,
  "dataframe_iter_index": 13074,
  "image_path": "./datasets/sVOC_FLUXFP8/images/13074.png",
  "image_width": 640,
  "image_height": 640,
  "ground_truth_class": "sheep",
  "grounding_prompt": "sheep",
  "timestamp": "2026-05-22T14:54:40.299954",
  "num_detections": 3,
  "detections": [
    {
      "detection_id": 0,
      "class_name": "sheep",
      "yolo_class_id": 16,
      "confidence": 0.8465385437011719,
      "bbox_xyxy": [
        65.06599426269531,
        237.44313049316406,
        264.2080078125,
        538.2899169921875
      ],
      "bbox_yolo": [
        0.2572453022003174,
        0.606041431427002,
        0.3111594021320343,
        0.4700731337070465
      ],
      "bbox_width_px": 199.1420135498047,
      "bbox_height_px": 300.8468017578125
    },
    {
      "detection_id": 1,
      "class_name": "sheep",
      "yolo_class_id": 16,
      "confidence": 0.8476325273513794,
      "bbox_xyxy": [
        374.5736083984375,
        256.4757995605469,
        587.55419921875,
        536.5838623046875
      ],
      "bbox_yolo": [
        0.7516623735427856,
        0.6195778846740723,
        0.33278217911720276,
        0.4376688599586487
      ],
      "bbox_width_px": 212.9805908203125,
      "bbox_height_px": 280.1080627441406
    },
    {
      "detection_id": 2,
      "class_name": "sheep",
      "yolo_class_id": 16,
      "confidence": 0.8327211737632751,
      "bbox_xyxy": [
        221.00888061523438,
        226.5675048828125,
        397.4966125488281,
        543.8643798828125
      ],
      "bbox_yolo": [
        0.4832074046134949,
        0.6018999218940735,
        0.27576208114624023,
        0.49577635526657104
      ],
      "bbox_width_px": 176.48773193359375,
      "bbox_height_px": 317.296875
    }
  ]
}