{
  "index": 13539,
  "dataframe_iter_index": 13539,
  "image_path": "./datasets/sVOC_FLUXFP8/images/13539.png",
  "image_width": 640,
  "image_height": 640,
  "ground_truth_class": "sheep",
  "grounding_prompt": "sheep",
  "timestamp": "2026-05-22T15:05:57.457025",
  "num_detections": 5,
  "detections": [
    {
      "detection_id": 0,
      "class_name": "sheep",
      "yolo_class_id": 16,
      "confidence": 0.7765684127807617,
      "bbox_xyxy": [
        122.23408508300781,
        253.80783081054688,
        296.18463134765625,
        486.8244934082031
      ],
      "bbox_yolo": [
        0.32688960433006287,
        0.5786190032958984,
        0.27179771661758423,
        0.3640885353088379
      ],
      "bbox_width_px": 173.95054626464844,
      "bbox_height_px": 233.01666259765625
    },
    {
      "detection_id": 1,
      "class_name": "sheep",
      "yolo_class_id": 16,
      "confidence": 0.7214672565460205,
      "bbox_xyxy": [
        330.50555419921875,
        261.1971435546875,
        470.20147705078125,
        493.01947021484375
      ],
      "bbox_yolo": [
        0.6255523562431335,
        0.5892317295074463,
        0.21827487647533417,
        0.3622223734855652
      ],
      "bbox_width_px": 139.6959228515625,
      "bbox_height_px": 231.82232666015625
    },
    {
      "detection_id": 2,
      "class_name": "sheep",
      "yolo_class_id": 16,
      "confidence": 0.7247995138168335,
      "bbox_xyxy": [
        435.1651916503906,
        287.80621337890625,
        606.8878173828125,
        451.20831298828125
      ],
      "bbox_yolo": [
        0.814103901386261,
        0.5773550868034363,
        0.2683165967464447,
        0.25531578063964844
      ],
      "bbox_width_px": 171.72262573242188,
      "bbox_height_px": 163.402099609375
    },
    {
      "detection_id": 3,
      "class_name": "sheep",
      "yolo_class_id": 16,
      "confidence": 0.44301638007164,
      "bbox_xyxy": [
        30.32050323486328,
        289.8560791015625,
        259.31976318359375,
        439.2376708984375
      ],
      "bbox_yolo": [
        0.22628144919872284,
        0.5696045160293579,
        0.3578113615512848,
        0.23340873420238495
      ],
      "bbox_width_px": 228.999267578125,
      "bbox_height_px": 149.381591796875
    },
    {
      "detection_id": 4,
      "class_name": "sheep",
      "yolo_class_id": 16,
      "confidence": 0.4495401978492737,
      "bbox_xyxy": [
        264.88836669921875,
        258.1770935058594,
        403.4373779296875,
        484.3799133300781
      ],
      "bbox_yolo": [
        0.522129476070404,
        0.5801226496696472,
        0.21648283302783966,
        0.35344189405441284
      ],
      "bbox_width_px": 138.54901123046875,
      "bbox_height_px": 226.20281982421875
    }
  ]
}