{
  "index": 13906,
  "dataframe_iter_index": 13906,
  "image_path": "./datasets/sVOC_FLUXFP8/images/13906.png",
  "image_width": 640,
  "image_height": 640,
  "ground_truth_class": "sofa",
  "grounding_prompt": "sofa",
  "timestamp": "2026-05-22T15:14:37.687326",
  "num_detections": 3,
  "detections": [
    {
      "detection_id": 0,
      "class_name": "sofa",
      "yolo_class_id": 17,
      "confidence": 0.7343713641166687,
      "bbox_xyxy": [
        426.3372802734375,
        438.7265319824219,
        588.300537109375,
        536.8232421875
      ],
      "bbox_yolo": [
        0.7926858067512512,
        0.7621482610702515,
        0.25306758284568787,
        0.15327611565589905
      ],
      "bbox_width_px": 161.9632568359375,
      "bbox_height_px": 98.09671020507812
    },
    {
      "detection_id": 1,
      "class_name": "sofa",
      "yolo_class_id": 17,
      "confidence": 0.6996639370918274,
      "bbox_xyxy": [
        52.426605224609375,
        437.99261474609375,
        217.0218505859375,
        535.9508056640625
      ],
      "bbox_yolo": [
        0.2105066031217575,
        0.7608932852745056,
        0.2571800649166107,
        0.1530596762895584
      ],
      "bbox_width_px": 164.59524536132812,
      "bbox_height_px": 97.95819091796875
    },
    {
      "detection_id": 2,
      "class_name": "sofa",
      "yolo_class_id": 17,
      "confidence": 0.7352239489555359,
      "bbox_xyxy": [
        244.16619873046875,
        433.11370849609375,
        401.93365478515625,
        518.6193237304688
      ],
      "bbox_yolo": [
        0.504765510559082,
        0.743541419506073,
        0.24651165306568146,
        0.13360252976417542
      ],
      "bbox_width_px": 157.7674560546875,
      "bbox_height_px": 85.505615234375
    }
  ]
}