{
  "index": 14181,
  "dataframe_iter_index": 14181,
  "image_path": "./datasets/sVOC_FLUXFP8/images/14181.png",
  "image_width": 640,
  "image_height": 640,
  "ground_truth_class": "sofa",
  "grounding_prompt": "sofa",
  "timestamp": "2026-05-22T15:21:05.546788",
  "num_detections": 2,
  "detections": [
    {
      "detection_id": 0,
      "class_name": "sofa",
      "yolo_class_id": 17,
      "confidence": 0.70559161901474,
      "bbox_xyxy": [
        13.45758056640625,
        309.00701904296875,
        243.77655029296875,
        527.8285522460938
      ],
      "bbox_yolo": [
        0.20096416771411896,
        0.6537777781486511,
        0.35987338423728943,
        0.34190863370895386
      ],
      "bbox_width_px": 230.3189697265625,
      "bbox_height_px": 218.821533203125
    },
    {
      "detection_id": 1,
      "class_name": "sofa",
      "yolo_class_id": 17,
      "confidence": 0.5565306544303894,
      "bbox_xyxy": [
        382.95770263671875,
        306.1590881347656,
        620.9005737304688,
        525.2733764648438
      ],
      "bbox_yolo": [
        0.7842642664909363,
        0.6495566368103027,
        0.3717857301235199,
        0.3423660695552826
      ],
      "bbox_width_px": 237.94287109375,
      "bbox_height_px": 219.11428833007812
    }
  ]
}