{
  "index": 14319,
  "dataframe_iter_index": 14319,
  "image_path": "./datasets/sVOC_FLUXFP8/images/14319.png",
  "image_width": 640,
  "image_height": 640,
  "ground_truth_class": "sofa",
  "grounding_prompt": "sofa",
  "timestamp": "2026-05-22T15:24:20.935576",
  "num_detections": 1,
  "detections": [
    {
      "detection_id": 0,
      "class_name": "sofa",
      "yolo_class_id": 17,
      "confidence": 0.9621671438217163,
      "bbox_xyxy": [
        72.65861511230469,
        256.7435607910156,
        558.6132202148438,
        547.1817626953125
      ],
      "bbox_yolo": [
        0.49318113923072815,
        0.6280666589736938,
        0.7593040466308594,
        0.4538096785545349
      ],
      "bbox_width_px": 485.95458984375,
      "bbox_height_px": 290.4382019042969
    }
  ]
}