{
  "index": 15217,
  "dataframe_iter_index": 15217,
  "image_path": "./datasets/sVOC_FLUXFP8/images/15217.png",
  "image_width": 640,
  "image_height": 640,
  "ground_truth_class": "tvmonitor",
  "grounding_prompt": "tvmonitor",
  "timestamp": "2026-05-22T15:45:24.556780",
  "num_detections": 2,
  "detections": [
    {
      "detection_id": 0,
      "class_name": "tvmonitor",
      "yolo_class_id": 19,
      "confidence": 0.5183371305465698,
      "bbox_xyxy": [
        319.79498291015625,
        222.981201171875,
        612.7883911132812,
        526.449951171875
      ],
      "bbox_yolo": [
        0.7285807728767395,
        0.5854930877685547,
        0.4578022062778473,
        0.47416990995407104
      ],
      "bbox_width_px": 292.993408203125,
      "bbox_height_px": 303.46875
    },
    {
      "detection_id": 1,
      "class_name": "tvmonitor",
      "yolo_class_id": 19,
      "confidence": 0.50081866979599,
      "bbox_xyxy": [
        28.628082275390625,
        217.28280639648438,
        318.5179443359375,
        533.72705078125
      ],
      "bbox_yolo": [
        0.2712078392505646,
        0.5867264866828918,
        0.45295292139053345,
        0.4944441318511963
      ],
      "bbox_width_px": 289.8898620605469,
      "bbox_height_px": 316.4442443847656
    }
  ]
}