{
  "index": 15270,
  "dataframe_iter_index": 15270,
  "image_path": "./datasets/sVOC_FLUXFP8/images/15270.png",
  "image_width": 640,
  "image_height": 640,
  "ground_truth_class": "tvmonitor",
  "grounding_prompt": "tvmonitor",
  "timestamp": "2026-05-22T15:46:39.701351",
  "num_detections": 3,
  "detections": [
    {
      "detection_id": 0,
      "class_name": "tvmonitor",
      "yolo_class_id": 19,
      "confidence": 0.7332995533943176,
      "bbox_xyxy": [
        263.0694885253906,
        189.91661071777344,
        367.7228698730469,
        279.073486328125
      ],
      "bbox_yolo": [
        0.4928065240383148,
        0.36639851331710815,
        0.1635209023952484,
        0.13930761814117432
      ],
      "bbox_width_px": 104.65338134765625,
      "bbox_height_px": 89.15687561035156
    },
    {
      "detection_id": 1,
      "class_name": "tvmonitor",
      "yolo_class_id": 19,
      "confidence": 0.7013123631477356,
      "bbox_xyxy": [
        395.1640319824219,
        220.83172607421875,
        492.4853820800781,
        305.1458740234375
      ],
      "bbox_yolo": [
        0.6934760808944702,
        0.41091999411582947,
        0.15206460654735565,
        0.13174085319042206
      ],
      "bbox_width_px": 97.32135009765625,
      "bbox_height_px": 84.31414794921875
    },
    {
      "detection_id": 2,
      "class_name": "tvmonitor",
      "yolo_class_id": 19,
      "confidence": 0.6731086373329163,
      "bbox_xyxy": [
        139.88075256347656,
        225.78683471679688,
        236.31919860839844,
        306.0813903808594
      ],
      "bbox_yolo": [
        0.29390621185302734,
        0.415522038936615,
        0.15068507194519043,
        0.12546023726463318
      ],
      "bbox_width_px": 96.43844604492188,
      "bbox_height_px": 80.2945556640625
    }
  ]
}