{
  "index": 519,
  "dataframe_iter_index": 519,
  "image_path": "./datasets/sVOC_FLUXFP8/images/519.png",
  "image_width": 640,
  "image_height": 640,
  "ground_truth_class": "aeroplane",
  "grounding_prompt": "aeroplane",
  "timestamp": "2026-05-22T10:15:55.669602",
  "num_detections": 3,
  "detections": [
    {
      "detection_id": 0,
      "class_name": "aeroplane",
      "yolo_class_id": 0,
      "confidence": 0.589046835899353,
      "bbox_xyxy": [
        97.14186096191406,
        342.5803527832031,
        156.3799591064453,
        355.3977966308594
      ],
      "bbox_yolo": [
        0.198063924908638,
        0.5452954173088074,
        0.09255953133106232,
        0.02002725563943386
      ],
      "bbox_width_px": 59.23809814453125,
      "bbox_height_px": 12.81744384765625
    },
    {
      "detection_id": 1,
      "class_name": "aeroplane",
      "yolo_class_id": 0,
      "confidence": 0.5431134104728699,
      "bbox_xyxy": [
        272.53411865234375,
        111.80632019042969,
        311.751220703125,
        127.18788146972656
      ],
      "bbox_yolo": [
        0.4564729332923889,
        0.18671421706676483,
        0.06127672269940376,
        0.024033689871430397
      ],
      "bbox_width_px": 39.21710205078125,
      "bbox_height_px": 15.381561279296875
    },
    {
      "detection_id": 2,
      "class_name": "aeroplane",
      "yolo_class_id": 0,
      "confidence": 0.54080730676651,
      "bbox_xyxy": [
        502.92822265625,
        63.665042877197266,
        551.594970703125,
        84.37094116210938
      ],
      "bbox_yolo": [
        0.8238462209701538,
        0.11565311253070831,
        0.0760417953133583,
        0.03235296532511711
      ],
      "bbox_width_px": 48.666748046875,
      "bbox_height_px": 20.70589828491211
    }
  ]
}