{
  "index": 5800,
  "dataframe_iter_index": 5800,
  "image_path": "./datasets/sVOC_FLUXFP8/images/5800.png",
  "image_width": 640,
  "image_height": 640,
  "ground_truth_class": "cat",
  "grounding_prompt": "cat",
  "timestamp": "2026-05-22T12:02:18.772165",
  "num_detections": 1,
  "detections": [
    {
      "detection_id": 0,
      "class_name": "cat",
      "yolo_class_id": 7,
      "confidence": 0.9676874876022339,
      "bbox_xyxy": [
        128.11813354492188,
        235.54620361328125,
        376.2490539550781,
        638.525390625
      ],
      "bbox_yolo": [
        0.3940368592739105,
        0.6828684210777283,
        0.3877045512199402,
        0.6296550035476685
      ],
      "bbox_width_px": 248.13092041015625,
      "bbox_height_px": 402.97918701171875
    }
  ]
}