{
  "index": 6950,
  "dataframe_iter_index": 6950,
  "image_path": "./datasets/sVOC_FLUXFP8/images/6950.png",
  "image_width": 640,
  "image_height": 640,
  "ground_truth_class": "chair",
  "grounding_prompt": "chair",
  "timestamp": "2026-05-22T12:29:06.689854",
  "num_detections": 3,
  "detections": [
    {
      "detection_id": 0,
      "class_name": "chair",
      "yolo_class_id": 8,
      "confidence": 0.6831865906715393,
      "bbox_xyxy": [
        248.55657958984375,
        333.78326416015625,
        372.21209716796875,
        582.2772827148438
      ],
      "bbox_yolo": [
        0.48497551679611206,
        0.7156723141670227,
        0.19321174919605255,
        0.38827189803123474
      ],
      "bbox_width_px": 123.655517578125,
      "bbox_height_px": 248.4940185546875
    },
    {
      "detection_id": 1,
      "class_name": "chair",
      "yolo_class_id": 8,
      "confidence": 0.7068178057670593,
      "bbox_xyxy": [
        458.5738830566406,
        347.83636474609375,
        587.9610595703125,
        576.6264038085938
      ],
      "bbox_yolo": [
        0.8176053762435913,
        0.7222365140914917,
        0.20216746628284454,
        0.3574844300746918
      ],
      "bbox_width_px": 129.38717651367188,
      "bbox_height_px": 228.7900390625
    },
    {
      "detection_id": 2,
      "class_name": "chair",
      "yolo_class_id": 8,
      "confidence": 0.6995561718940735,
      "bbox_xyxy": [
        60.62957763671875,
        340.30230712890625,
        193.90896606445312,
        578.8896484375
      ],
      "bbox_yolo": [
        0.19885823130607605,
        0.7181187272071838,
        0.2082490473985672,
        0.37279272079467773
      ],
      "bbox_width_px": 133.27938842773438,
      "bbox_height_px": 238.58734130859375
    }
  ]
}