{
  "index": 8395,
  "dataframe_iter_index": 8395,
  "image_path": "./datasets/sVOC_FLUXFP8/images/8395.png",
  "image_width": 640,
  "image_height": 640,
  "ground_truth_class": "diningtable",
  "grounding_prompt": "diningtable",
  "timestamp": "2026-05-22T13:02:50.087860",
  "num_detections": 1,
  "detections": [
    {
      "detection_id": 0,
      "class_name": "diningtable",
      "yolo_class_id": 10,
      "confidence": 0.42054325342178345,
      "bbox_xyxy": [
        71.87690734863281,
        330.98187255859375,
        378.814208984375,
        577.3485107421875
      ],
      "bbox_yolo": [
        0.3521024286746979,
        0.7096331119537354,
        0.4795895516872406,
        0.38494786620140076
      ],
      "bbox_width_px": 306.93731689453125,
      "bbox_height_px": 246.36663818359375
    }
  ]
}