{
  "index": 9115,
  "dataframe_iter_index": 9115,
  "image_path": "./datasets/sVOC_FLUXFP8/images/9115.png",
  "image_width": 640,
  "image_height": 640,
  "ground_truth_class": "dog",
  "grounding_prompt": "dog",
  "timestamp": "2026-05-22T13:19:26.212608",
  "num_detections": 1,
  "detections": [
    {
      "detection_id": 0,
      "class_name": "dog",
      "yolo_class_id": 11,
      "confidence": 0.9562239050865173,
      "bbox_xyxy": [
        90.34228515625,
        77.67669677734375,
        478.6644287109375,
        637.5625610351562
      ],
      "bbox_yolo": [
        0.4445365071296692,
        0.5587806701660156,
        0.6067533493041992,
        0.874821662902832
      ],
      "bbox_width_px": 388.3221435546875,
      "bbox_height_px": 559.8858642578125
    }
  ]
}