{
  "index": 255,
  "dataframe_iter_index": 255,
  "image_path": "./datasets/sFERNANDO_TUGBOATS_FLUXDEV/images/255.png",
  "image_width": 640,
  "image_height": 640,
  "ground_truth_class": "tugboat",
  "grounding_prompt": "boat",
  "timestamp": "2026-05-13T20:20:02.709624",
  "num_detections": 1,
  "detections": [
    {
      "detection_id": 0,
      "class_name": "tugboat",
      "yolo_class_id": 0,
      "confidence": 0.9067236185073853,
      "bbox_xyxy": [
        45.770538330078125,
        199.56802368164062,
        612.5799560546875,
        544.689453125
      ],
      "bbox_yolo": [
        0.5143362879753113,
        0.5814511179924011,
        0.8856397867202759,
        0.5392522215843201
      ],
      "bbox_width_px": 566.8094482421875,
      "bbox_height_px": 345.1214294433594
    }
  ]
}