{
  "index": 1429,
  "dataframe_iter_index": 1429,
  "image_path": "./datasets/sHOMEOBJECTS_FLUXFP8/images/1429.jpg",
  "image_width": 640,
  "image_height": 640,
  "ground_truth_class": "sofa",
  "grounding_prompt": "sofa",
  "timestamp": "2026-05-15T23:02:39.482391",
  "num_detections": 2,
  "detections": [
    {
      "detection_id": 0,
      "class_name": "sofa",
      "yolo_class_id": 4,
      "confidence": 0.844640851020813,
      "bbox_xyxy": [
        0.246185302734375,
        308.1886901855469,
        256.589599609375,
        600.2109375
      ],
      "bbox_yolo": [
        0.20065295696258545,
        0.7096872329711914,
        0.40053659677505493,
        0.456284761428833
      ],
      "bbox_width_px": 256.3434143066406,
      "bbox_height_px": 292.0222473144531
    },
    {
      "detection_id": 1,
      "class_name": "sofa",
      "yolo_class_id": 4,
      "confidence": 0.8276272416114807,
      "bbox_xyxy": [
        388.7203674316406,
        306.5022277832031,
        639.3955688476562,
        600.29541015625
      ],
      "bbox_yolo": [
        0.8032156229019165,
        0.7084356546401978,
        0.3916800022125244,
        0.45905184745788574
      ],
      "bbox_width_px": 250.67520141601562,
      "bbox_height_px": 293.7931823730469
    }
  ]
}