{
  "index": 1736,
  "dataframe_iter_index": 1736,
  "image_path": "./datasets/sHOMEOBJECTS_FLUXFP8/images/1736.jpg",
  "image_width": 640,
  "image_height": 640,
  "ground_truth_class": "bed",
  "grounding_prompt": "bed",
  "timestamp": "2026-05-15T23:09:32.065450",
  "num_detections": 2,
  "detections": [
    {
      "detection_id": 0,
      "class_name": "bed",
      "yolo_class_id": 0,
      "confidence": 0.45206418633461,
      "bbox_xyxy": [
        103.84719848632812,
        300.8438415527344,
        549.0760498046875,
        594.5084228515625
      ],
      "bbox_yolo": [
        0.5100962519645691,
        0.6994940042495728,
        0.6956700682640076,
        0.4588509202003479
      ],
      "bbox_width_px": 445.2288513183594,
      "bbox_height_px": 293.6645812988281
    },
    {
      "detection_id": 1,
      "class_name": "bed",
      "yolo_class_id": 0,
      "confidence": 0.37818366289138794,
      "bbox_xyxy": [
        104.37681579589844,
        369.0745849609375,
        531.7998657226562,
        594.4777221679688
      ],
      "bbox_yolo": [
        0.49701303243637085,
        0.752775251865387,
        0.6678484678268433,
        0.35219240188598633
      ],
      "bbox_width_px": 427.42303466796875,
      "bbox_height_px": 225.40313720703125
    }
  ]
}