{
  "index": 1988,
  "dataframe_iter_index": 1988,
  "image_path": "./datasets/sHOMEOBJECTS_FLUXFP8/images/1988.jpg",
  "image_width": 640,
  "image_height": 640,
  "ground_truth_class": "bed",
  "grounding_prompt": "bed",
  "timestamp": "2026-05-15T23:15:10.892543",
  "num_detections": 1,
  "detections": [
    {
      "detection_id": 0,
      "class_name": "bed",
      "yolo_class_id": 0,
      "confidence": 0.9107099175453186,
      "bbox_xyxy": [
        124.84420776367188,
        289.5184631347656,
        571.6690673828125,
        516.0839233398438
      ],
      "bbox_yolo": [
        0.5441510081291199,
        0.6293768882751465,
        0.6981638669967651,
        0.3540085256099701
      ],
      "bbox_width_px": 446.8248596191406,
      "bbox_height_px": 226.56546020507812
    }
  ]
}