{
  "index": 2024,
  "dataframe_iter_index": 2024,
  "image_path": "./datasets/sHOMEOBJECTS_FLUXFP8/images/2024.jpg",
  "image_width": 640,
  "image_height": 640,
  "ground_truth_class": "bed",
  "grounding_prompt": "bed",
  "timestamp": "2026-05-15T23:15:59.074590",
  "num_detections": 1,
  "detections": [
    {
      "detection_id": 0,
      "class_name": "bed",
      "yolo_class_id": 0,
      "confidence": 0.8801600933074951,
      "bbox_xyxy": [
        101.67338562011719,
        307.5640563964844,
        593.9010009765625,
        608.5460205078125
      ],
      "bbox_yolo": [
        0.5434175133705139,
        0.7157109975814819,
        0.7691056132316589,
        0.4702843129634857
      ],
      "bbox_width_px": 492.22760009765625,
      "bbox_height_px": 300.9819641113281
    }
  ]
}