{
  "index": 2515,
  "dataframe_iter_index": 2515,
  "image_path": "./datasets/sHOMEOBJECTS_FLUXFP8/images/2515.jpg",
  "image_width": 640,
  "image_height": 640,
  "ground_truth_class": "lamp",
  "grounding_prompt": "lamp",
  "timestamp": "2026-05-15T23:27:07.027143",
  "num_detections": 2,
  "detections": [
    {
      "detection_id": 0,
      "class_name": "lamp",
      "yolo_class_id": 2,
      "confidence": 0.8034323453903198,
      "bbox_xyxy": [
        396.41204833984375,
        151.18482971191406,
        427.9453125,
        261.73077392578125
      ],
      "bbox_yolo": [
        0.6440292000770569,
        0.32259029150009155,
        0.04927072674036026,
        0.172728031873703
      ],
      "bbox_width_px": 31.53326416015625,
      "bbox_height_px": 110.54594421386719
    },
    {
      "detection_id": 1,
      "class_name": "lamp",
      "yolo_class_id": 2,
      "confidence": 0.5550873875617981,
      "bbox_xyxy": [
        239.94827270507812,
        209.8453826904297,
        250.81362915039062,
        232.2438507080078
      ],
      "bbox_yolo": [
        0.38340774178504944,
        0.3453822135925293,
        0.01697712019085884,
        0.0349976047873497
      ],
      "bbox_width_px": 10.8653564453125,
      "bbox_height_px": 22.398468017578125
    }
  ]
}