{
  "index": 2651,
  "dataframe_iter_index": 2651,
  "image_path": "./datasets/sHOMEOBJECTS_FLUXFP8/images/2651.jpg",
  "image_width": 640,
  "image_height": 640,
  "ground_truth_class": "television",
  "grounding_prompt": "television",
  "timestamp": "2026-05-15T23:30:12.464478",
  "num_detections": 1,
  "detections": [
    {
      "detection_id": 0,
      "class_name": "television",
      "yolo_class_id": 6,
      "confidence": 0.9116657972335815,
      "bbox_xyxy": [
        108.72369384765625,
        236.70101928710938,
        280.3650817871094,
        370.1471252441406
      ],
      "bbox_yolo": [
        0.3039756119251251,
        0.47410011291503906,
        0.2681896686553955,
        0.20850953459739685
      ],
      "bbox_width_px": 171.64138793945312,
      "bbox_height_px": 133.44610595703125
    }
  ]
}