{
  "index": 2935,
  "dataframe_iter_index": 2935,
  "image_path": "./datasets/sHOMEOBJECTS_FLUXFP8/images/2935.jpg",
  "image_width": 640,
  "image_height": 640,
  "ground_truth_class": "television",
  "grounding_prompt": "television",
  "timestamp": "2026-05-15T23:36:27.823336",
  "num_detections": 1,
  "detections": [
    {
      "detection_id": 0,
      "class_name": "television",
      "yolo_class_id": 6,
      "confidence": 0.8616551756858826,
      "bbox_xyxy": [
        235.4261474609375,
        11.864501953125,
        560.3895874023438,
        388.5664367675781
      ],
      "bbox_yolo": [
        0.6217310428619385,
        0.3128366768360138,
        0.5077553987503052,
        0.588596761226654
      ],
      "bbox_width_px": 324.96343994140625,
      "bbox_height_px": 376.7019348144531
    }
  ]
}