{
  "index": 56,
  "dataframe_iter_index": 56,
  "image_path": "./datasets/sHOMEOBJECTS_FLUXFP8/images/56.jpg",
  "image_width": 640,
  "image_height": 640,
  "ground_truth_class": "chair",
  "grounding_prompt": "chair",
  "timestamp": "2026-05-15T22:31:44.726650",
  "num_detections": 1,
  "detections": [
    {
      "detection_id": 0,
      "class_name": "chair",
      "yolo_class_id": 1,
      "confidence": 0.9108068943023682,
      "bbox_xyxy": [
        176.31320190429688,
        234.31394958496094,
        501.9907531738281,
        590.6182250976562
      ],
      "bbox_yolo": [
        0.5299249887466431,
        0.6444782614707947,
        0.5088711977005005,
        0.5567253828048706
      ],
      "bbox_width_px": 325.67755126953125,
      "bbox_height_px": 356.30426025390625
    }
  ]
}