{
  "index": 870,
  "dataframe_iter_index": 870,
  "image_path": "./datasets/sHOMEOBJECTS_FLUXFP8/images/870.jpg",
  "image_width": 640,
  "image_height": 640,
  "ground_truth_class": "table",
  "grounding_prompt": "table",
  "timestamp": "2026-05-15T22:50:06.092109",
  "num_detections": 4,
  "detections": [
    {
      "detection_id": 0,
      "class_name": "table",
      "yolo_class_id": 5,
      "confidence": 0.7080690264701843,
      "bbox_xyxy": [
        11.63555908203125,
        365.80694580078125,
        230.16799926757812,
        589.1689453125
      ],
      "bbox_yolo": [
        0.18890902400016785,
        0.746074914932251,
        0.34145694971084595,
        0.3490031361579895
      ],
      "bbox_width_px": 218.53244018554688,
      "bbox_height_px": 223.36199951171875
    },
    {
      "detection_id": 1,
      "class_name": "table",
      "yolo_class_id": 5,
      "confidence": 0.4424879550933838,
      "bbox_xyxy": [
        342.52764892578125,
        322.4215087890625,
        458.96600341796875,
        374.69671630859375
      ],
      "bbox_yolo": [
        0.6261669397354126,
        0.544623613357544,
        0.1819349229335785,
        0.08168001472949982
      ],
      "bbox_width_px": 116.4383544921875,
      "bbox_height_px": 52.27520751953125
    },
    {
      "detection_id": 2,
      "class_name": "table",
      "yolo_class_id": 5,
      "confidence": 0.6605453491210938,
      "bbox_xyxy": [
        368.2938537597656,
        370.61865234375,
        615.16455078125,
        598.2401123046875
      ],
      "bbox_yolo": [
        0.7683268785476685,
        0.7569209337234497,
        0.3857354521751404,
        0.35565853118896484
      ],
      "bbox_width_px": 246.87069702148438,
      "bbox_height_px": 227.6214599609375
    },
    {
      "detection_id": 3,
      "class_name": "table",
      "yolo_class_id": 5,
      "confidence": 0.4830702841281891,
      "bbox_xyxy": [
        151.31605529785156,
        322.3250427246094,
        264.4657287597656,
        435.4483947753906
      ],
      "bbox_yolo": [
        0.3248295187950134,
        0.592010498046875,
        0.17679636180400848,
        0.17675523459911346
      ],
      "bbox_width_px": 113.14967346191406,
      "bbox_height_px": 113.12335205078125
    }
  ]
}